word_cluster_tcr/__init__.py
word_cluster_tcr/cli.py
word_cluster_tcr/word_cluster_tcr.py
word_cluster_tcr-0.3.0.dist-info/AUTHORS.rst
word_cluster_tcr-0.3.0.dist-info/LICENSE
word_cluster_tcr-0.3.0.dist-info/METADATA
word_cluster_tcr-0.3.0.dist-info/WHEEL
word_cluster_tcr-0.3.0.dist-info/entry_points.txt
word_cluster_tcr-0.3.0.dist-info/top_level.txt
word_cluster_tcr-0.3.0.dist-info/RECORD
