Metadata-Version: 2.1
Name: word-cluster-tcr
Version: 0.3.0
Summary: cluster cdr3 amino acid sequences
Home-page: https://github.com/idohasson/word_cluster_tcr
Author: ido hasson
Author-email: ido.hasson.5@gmail.com
License: MIT license
Keywords: word_cluster_tcr
Classifier: Development Status :: 2 - Pre-Alpha
Classifier: Intended Audience :: Developers
Classifier: License :: OSI Approved :: MIT License
Classifier: Natural Language :: English
Classifier: Programming Language :: Python :: 3
Classifier: Programming Language :: Python :: 3.6
Classifier: Programming Language :: Python :: 3.7
Classifier: Programming Language :: Python :: 3.8
Requires-Python: >=3.6
License-File: LICENSE
License-File: AUTHORS.rst
